stsmfa/__init__.py
stsmfa/__maIn__.py
stsmfa/cli.py
stsmfa/py.typed
stsmfa_cli-1.7.0.dist-info/licenses/LICENSE
stsmfa_cli-1.7.0.dist-info/METADATA
stsmfa_cli-1.7.0.dist-info/WHEEL
stsmfa_cli-1.7.0.dist-info/entry_points.txt
stsmfa_cli-1.7.0.dist-info/top_level.txt
stsmfa_cli-1.7.0.dist-info/RECORD
