Metadata-Version: 2.4
Name: stsmfa-cli
Version: 1.7.0
Summary: A small CLI to help with creating AWS profile for MFA protected sessions
Author-email: Bruno Alla <alla.brunoo@gmail.com>
License: MIT
Project-URL: Bug Tracker, https://github.com/browniebroke/stsmfa-cli/issues
Project-URL: Changelog, https://github.com/browniebroke/stsmfa-cli/blob/main/CHANGELOG.md
Project-URL: repository, https://github.com/browniebroke/stsmfa-cli
Classifier: Development Status :: 2 - Pre-Alpha
Classifier: Intended Audience :: Developers
Classifier: Natural Language :: English
Classifier: Operating System :: OS Independent
Classifier: Programming Language :: Python :: 3 :: Only
Classifier: Programming Language :: Python :: 3.10
Classifier: Programming Language :: Python :: 3.11
Classifier: Programming Language :: Python :: 3.12
Classifier: Programming Language :: Python :: 3.13
Classifier: Programming Language :: Python :: 3.14
Classifier: Topic :: Software Development :: Libraries
Requires-Python: >=3.10
License-File: LICENSE
Requires-Dist: boto3<2,>=1.26
Requires-Dist: rich>=10
Requires-Dist: typer<1,>=0.15
Dynamic: license-file
